jfrog_cdk_constructs/__init__.py
jfrog_cdk_constructs/py.typed
jfrog_cdk_constructs/_jsii/__init__.py
jfrog_cdk_constructs/_jsii/jfrog-cdk-constructs@1.0.6.jsii.tgz
jfrog_cdk_constructs-1.0.6.dist-info/LICENSE
jfrog_cdk_constructs-1.0.6.dist-info/METADATA
jfrog_cdk_constructs-1.0.6.dist-info/WHEEL
jfrog_cdk_constructs-1.0.6.dist-info/top_level.txt
jfrog_cdk_constructs-1.0.6.dist-info/RECORD
