Metadata-Version: 2.1
Name: jfrog-cdk-constructs
Version: 1.0.6
Summary: jfrog-cdk-constructs
Home-page: https://github.com/anshrma/jfrog-cdk-constructs.git
Author: Anuj Sharma<anshrma@amazon.com>
License: Apache-2.0
Project-URL: Source, https://github.com/anshrma/jfrog-cdk-constructs.git
Platform: UNKNOWN
Classifier: Intended Audience :: Developers
Classifier: Operating System :: OS Independent
Classifier: Programming Language :: JavaScript
Classifier: Programming Language :: Python :: 3 :: Only
Classifier: Programming Language :: Python :: 3.6
Classifier: Programming Language :: Python :: 3.7
Classifier: Programming Language :: Python :: 3.8
Classifier: Programming Language :: Python :: 3.9
Classifier: Typing :: Typed
Classifier: Development Status :: 5 - Production/Stable
Classifier: License :: OSI Approved
Requires-Python: >=3.6
Requires-Dist: aws-cdk.aws-ec2 (<2.0.0,>=1.100.0)
Requires-Dist: aws-cdk.aws-eks (<2.0.0,>=1.100.0)
Requires-Dist: aws-cdk.aws-iam (<2.0.0,>=1.100.0)
Requires-Dist: aws-cdk.aws-kms (<2.0.0,>=1.100.0)
Requires-Dist: aws-cdk.aws-rds (<2.0.0,>=1.100.0)
Requires-Dist: aws-cdk.aws-s3 (<2.0.0,>=1.100.0)
Requires-Dist: aws-cdk.core (<2.0.0,>=1.100.0)
Requires-Dist: constructs (<4.0.0,>=3.2.27)
Requires-Dist: jsii (<2.0.0,>=1.29.0)
Requires-Dist: publication (>=0.0.3)
